LICENSE
MANIFEST.in
README.md
requirements.txt
setup.cfg
setup.py
docker_registry/__init__.py
docker_registry/drivers/__init__.py
docker_registry/drivers/swift.py
docker_registry_driver_swift_glb.egg-info/PKG-INFO
docker_registry_driver_swift_glb.egg-info/SOURCES.txt
docker_registry_driver_swift_glb.egg-info/dependency_links.txt
docker_registry_driver_swift_glb.egg-info/namespace_packages.txt
docker_registry_driver_swift_glb.egg-info/pbr.json
docker_registry_driver_swift_glb.egg-info/requires.txt
docker_registry_driver_swift_glb.egg-info/top_level.txt
docker_registry_driver_swift_glb.egg-info/zip-safe
tests/requirements.txt