Metadata-Version: 1.1
Name: docker-registry-driver-swift-glb
Version: 0.2.2
Summary: Docker registry swift driver
Home-page: https://github.com/wagnersza/docker-registry-driver-swift-glb
Author: Wagner Souza
Author-email: wagnersza@gmail.com
License: Copyright 2014 Matthew Fisher <matthewf@opdemand.com>
